seelogs/__init__.py
seelogs/client.py
seelogs/types.py
seelogs/utils/__init__.py
seelogs/utils/network_info.py
seelogs/utils/system_info.py
seelogs/utils/utils.py
seelogs-1.0.1.dist-info/METADATA
seelogs-1.0.1.dist-info/WHEEL
seelogs-1.0.1.dist-info/licenses/LICENSE
seelogs-1.0.1.dist-info/RECORD
